{
  "date": "2026-06-29",
  "generated_utc": "2026-06-29T03:20:34.294783+00:00",
  "method": "sp-independent-team-strength",
  "note": "DISPLAY-ONLY provisional lean; never feeds the model or staking",
  "games": {
    "SD @ CHC": {
      "provisional_pick": "CHC",
      "p_pick": 0.704,
      "p_home": 0.704,
      "basis": "team-strength(win%+runDiff)+home-field",
      "confidence": "medium",
      "is_provisional": true,
      "no_sp": true,
      "away": "SD",
      "home": "CHC",
      "away_strength": 0.06,
      "home_strength": 0.73
    },
    "MIA @ COL": {
      "provisional_pick": "MIA",
      "p_pick": 0.866,
      "p_home": 0.134,
      "basis": "team-strength(win%+runDiff)+home-field",
      "confidence": "medium",
      "is_provisional": true,
      "no_sp": true,
      "away": "MIA",
      "home": "COL",
      "away_strength": 0.27,
      "home_strength": -1.66
    }
  }
}