{
  "schema_version": 1,
  "generated_at": "2026-06-24T16:32:50.960375Z",
  "slate_date": "2026-06-24",
  "matchups": {
    "TEX @ MIA": [
      {
        "game_number": 1,
        "label": "G3 of 3"
      }
    ],
    "CHC @ NYM": [
      {
        "game_number": 1,
        "label": "G2 of 4"
      },
      {
        "game_number": 2,
        "label": "G3 of 4"
      }
    ],
    "CLE @ CWS": [
      {
        "game_number": 1,
        "label": "G3 of 3"
      }
    ],
    "BOS @ COL": [
      {
        "game_number": 1,
        "label": "G3 of 3"
      }
    ],
    "BAL @ LAA": [
      {
        "game_number": 1,
        "label": "G3 of 3"
      }
    ],
    "SEA @ PIT": [
      {
        "game_number": 1,
        "label": "G2 of 3"
      }
    ],
    "KC @ TB": [
      {
        "game_number": 1,
        "label": "G3 of 4"
      }
    ],
    "NYY @ DET": [
      {
        "game_number": 1,
        "label": "G3 of 3"
      }
    ],
    "PHI @ WSH": [
      {
        "game_number": 1,
        "label": "G3 of 4"
      }
    ],
    "HOU @ TOR": [
      {
        "game_number": 1,
        "label": "G3 of 3"
      }
    ],
    "MIL @ CIN": [
      {
        "game_number": 1,
        "label": "G3 of 3"
      }
    ],
    "LAD @ MIN": [
      {
        "game_number": 1,
        "label": "G3 of 3"
      }
    ],
    "AZ @ STL": [
      {
        "game_number": 1,
        "label": "G3 of 4"
      }
    ],
    "ATL @ SD": [
      {
        "game_number": 1,
        "label": "G3 of 3"
      }
    ],
    "ATH @ SF": [
      {
        "game_number": 1,
        "label": "G2 of 3"
      }
    ]
  }
}