{
 "date": "2026-06-26",
 "generated_utc": "2026-06-25T09:33:04+00:00",
 "method": "effWind=speed*coef*alt*cos(windTo-cfBearing); tilt=0.6*wind+0.25*temp+0.15*elev-0.5*wet; DISPLAY ONLY",
 "games": {
  "HOU @ DET": {
   "indoor": false,
   "badge": "NEUTRAL",
   "runs_tilt": -0.053,
   "eff_wind": -1.9,
   "dir": "in",
   "wind_mph": 7.9,
   "wind_from": 83,
   "cf_bearing": 150,
   "temp_f": 75.5,
   "precip_pct": 20,
   "code": 3,
   "wet": false,
   "retractable": false,
   "why": "wind 8 mph crosswind/calm",
   "stadium": "Comerica Park",
   "home": "DET",
   "first_pitch_utc": "2026-06-26T22:40:00Z",
   "forecast_hour": "2026-06-26T22:00"
  },
  "TEX @ TOR": {
   "indoor": false,
   "badge": "WET?",
   "runs_tilt": -0.231,
   "eff_wind": 0.2,
   "dir": "out",
   "wind_mph": 1.2,
   "wind_from": 248,
   "cf_bearing": 0,
   "temp_f": 66.8,
   "precip_pct": 7,
   "code": 53,
   "wet": true,
   "retractable": true,
   "why": "rain/storm risk (precip 7%) - fewer runs / delay risk; retractable roof - may be closed",
   "stadium": "Rogers Centre",
   "home": "TOR",
   "first_pitch_utc": "2026-06-26T23:07:00Z",
   "forecast_hour": "2026-06-26T23:00"
  },
  "NYY @ BOS": {
   "indoor": false,
   "badge": "NEUTRAL",
   "runs_tilt": 0.201,
   "eff_wind": 4.0,
   "dir": "out",
   "wind_mph": 7.6,
   "wind_from": 183,
   "cf_bearing": 45,
   "temp_f": 70.4,
   "precip_pct": 33,
   "code": 3,
   "wet": false,
   "retractable": false,
   "why": "wind 8 mph crosswind/calm",
   "stadium": "Fenway Park",
   "home": "BOS",
   "first_pitch_utc": "2026-06-26T23:10:00Z",
   "forecast_hour": "2026-06-26T23:00"
  },
  "COL @ MIN": {
   "indoor": false,
   "badge": "NEUTRAL",
   "runs_tilt": -0.061,
   "eff_wind": -2.1,
   "dir": "in",
   "wind_mph": 4.8,
   "wind_from": 53,
   "cf_bearing": 100,
   "temp_f": 76.3,
   "precip_pct": 2,
   "code": 3,
   "wet": false,
   "retractable": false,
   "why": "wind 5 mph crosswind/calm",
   "stadium": "Target Field",
   "home": "MIN",
   "first_pitch_utc": "2026-06-27T00:10:00Z",
   "forecast_hour": "2026-06-27T00:00"
  },
  "MIA @ STL": {
   "indoor": false,
   "badge": "WET",
   "runs_tilt": -0.234,
   "eff_wind": 4.3,
   "dir": "out",
   "wind_mph": 7.6,
   "wind_from": 199,
   "cf_bearing": 0,
   "temp_f": 77.0,
   "precip_pct": 87,
   "code": 3,
   "wet": true,
   "retractable": false,
   "why": "rain/storm risk (precip 87%) - fewer runs / delay risk",
   "stadium": "Busch Stadium",
   "home": "STL",
   "first_pitch_utc": "2026-06-27T00:15:00Z",
   "forecast_hour": "2026-06-27T00:00"
  },
  "LAD @ SD": {
   "indoor": false,
   "badge": "NEUTRAL",
   "runs_tilt": -0.045,
   "eff_wind": -0.4,
   "dir": "in",
   "wind_mph": 5.4,
   "wind_from": 277,
   "cf_bearing": 0,
   "temp_f": 66.2,
   "precip_pct": 0,
   "code": 3,
   "wet": false,
   "retractable": false,
   "why": "wind 5 mph crosswind/calm",
   "stadium": "Petco Park",
   "home": "SD",
   "first_pitch_utc": "2026-06-27T01:45:00Z",
   "forecast_hour": "2026-06-27T01:00"
  },
  "CIN @ PIT": {
   "indoor": false,
   "badge": "NEUTRAL",
   "runs_tilt": 0.063,
   "eff_wind": -0.8,
   "dir": "in",
   "wind_mph": 6.7,
   "wind_from": 272,
   "cf_bearing": 350,
   "temp_f": 84.2,
   "precip_pct": 24,
   "code": 3,
   "wet": false,
   "retractable": false,
   "why": "wind 7 mph crosswind/calm",
   "stadium": "PNC Park",
   "home": "PIT",
   "first_pitch_utc": "2026-06-26T22:40:00Z",
   "forecast_hour": "2026-06-26T22:00"
  },
  "WSH @ BAL": {
   "indoor": false,
   "badge": "NEUTRAL",
   "runs_tilt": 0.241,
   "eff_wind": 2.3,
   "dir": "out",
   "wind_mph": 3.8,
   "wind_from": 230,
   "cf_bearing": 30,
   "temp_f": 91.2,
   "precip_pct": 31,
   "code": 3,
   "wet": false,
   "retractable": false,
   "why": "wind 4 mph crosswind/calm; hot 91 F (+carry)",
   "stadium": "Oriole Park at Camden Yards",
   "home": "BAL",
   "first_pitch_utc": "2026-06-26T23:05:00Z",
   "forecast_hour": "2026-06-26T23:00"
  },
  "SEA @ CLE": {
   "indoor": false,
   "badge": "NEUTRAL",
   "runs_tilt": -0.141,
   "eff_wind": -3.2,
   "dir": "in",
   "wind_mph": 5.5,
   "wind_from": 14,
   "cf_bearing": 0,
   "temp_f": 72.7,
   "precip_pct": 21,
   "code": 3,
   "wet": false,
   "retractable": false,
   "why": "wind 6 mph crosswind/calm",
   "stadium": "Progressive Field",
   "home": "CLE",
   "first_pitch_utc": "2026-06-26T23:10:00Z",
   "forecast_hour": "2026-06-26T23:00"
  },
  "ARI @ TB": {
   "indoor": true,
   "badge": "INDOOR",
   "runs_tilt": 0.0,
   "why": "Indoor dome - weather not a factor",
   "stadium": "Tropicana Field",
   "home": "TB",
   "first_pitch_utc": "2026-06-26T23:10:00Z",
   "forecast_hour": "2026-06-26T23:00"
  },
  "PHI @ NYM": {
   "indoor": false,
   "badge": "OUT",
   "runs_tilt": 0.316,
   "eff_wind": 5.0,
   "dir": "out",
   "wind_mph": 10.0,
   "wind_from": 164,
   "cf_bearing": 28,
   "temp_f": 79.6,
   "precip_pct": 2,
   "code": 3,
   "wet": false,
   "retractable": false,
   "why": "5 mph blowing OUT to CF (+runs)",
   "stadium": "Citi Field",
   "home": "NYM",
   "first_pitch_utc": "2026-06-26T23:10:00Z",
   "forecast_hour": "2026-06-26T23:00"
  },
  "KC @ CHW": {
   "indoor": false,
   "badge": "NEUTRAL",
   "runs_tilt": -0.185,
   "eff_wind": -3.3,
   "dir": "in",
   "wind_mph": 10.1,
   "wind_from": 76,
   "cf_bearing": 135,
   "temp_f": 67.3,
   "precip_pct": 39,
   "code": 3,
   "wet": false,
   "retractable": false,
   "why": "wind 10 mph crosswind/calm",
   "stadium": "Rate Field",
   "home": "CHW",
   "first_pitch_utc": "2026-06-26T23:40:00Z",
   "forecast_hour": "2026-06-26T23:00"
  },
  "CHC @ MIL": {
   "indoor": false,
   "badge": "NEUTRAL",
   "runs_tilt": 0.032,
   "eff_wind": 1.0,
   "dir": "out",
   "wind_mph": 6.5,
   "wind_from": 59,
   "cf_bearing": 170,
   "temp_f": 67.2,
   "precip_pct": 4,
   "code": 0,
   "wet": false,
   "retractable": true,
   "why": "wind 6 mph crosswind/calm; retractable roof - may be closed",
   "stadium": "American Family Field",
   "home": "MIL",
   "first_pitch_utc": "2026-06-26T23:45:00Z",
   "forecast_hour": "2026-06-26T23:00"
  },
  "OAK @ LAA": {
   "indoor": false,
   "badge": "OUT",
   "runs_tilt": 0.248,
   "eff_wind": 5.0,
   "dir": "out",
   "wind_mph": 8.9,
   "wind_from": 227,
   "cf_bearing": 45,
   "temp_f": 69.6,
   "precip_pct": 0,
   "code": 0,
   "wet": false,
   "retractable": false,
   "why": "5 mph blowing OUT to CF (+runs)",
   "stadium": "Angel Stadium",
   "home": "LAA",
   "first_pitch_utc": "2026-06-27T01:38:00Z",
   "forecast_hour": "2026-06-27T01:00"
  },
  "ATL @ SF": {
   "indoor": false,
   "badge": "OUT",
   "runs_tilt": 0.437,
   "eff_wind": 10.3,
   "dir": "out",
   "wind_mph": 11.9,
   "wind_from": 274,
   "cf_bearing": 80,
   "temp_f": 58.9,
   "precip_pct": 2,
   "code": 3,
   "wet": false,
   "retractable": false,
   "why": "10 mph blowing OUT to CF (+runs)",
   "stadium": "Oracle Park",
   "home": "SF",
   "first_pitch_utc": "2026-06-27T02:15:00Z",
   "forecast_hour": "2026-06-27T02:00"
  }
 }
}